modula/__init__.py
modula/abstract.py
modula/atom.py
modula/bond.py
modula/compound.py
modula/vector.py
modula-0.0.0.0.0.2.dist-info/LICENSE
modula-0.0.0.0.0.2.dist-info/METADATA
modula-0.0.0.0.0.2.dist-info/WHEEL
modula-0.0.0.0.0.2.dist-info/top_level.txt
modula-0.0.0.0.0.2.dist-info/RECORD
